ltbio/__init__.py
ltbio/_core/__init__.py
ltbio/_core/exceptions.py
ltbio/_core/operations.py
ltbio/_core/statistics.py
ltbio/biosignals/__init__.py
ltbio/biosignals/statistics.py
ltbio/biosignals/modalities/ACC.py
ltbio/biosignals/modalities/Biosignal.py
ltbio/biosignals/modalities/ECG.py
ltbio/biosignals/modalities/EDA.py
ltbio/biosignals/modalities/EEG.py
ltbio/biosignals/modalities/EMG.py
ltbio/biosignals/modalities/HR.py
ltbio/biosignals/modalities/MultimodalBiosignal.py
ltbio/biosignals/modalities/PPG.py
ltbio/biosignals/modalities/RESP.py
ltbio/biosignals/modalities/TEMP.py
ltbio/biosignals/modalities/__init__.py
ltbio/biosignals/sources/BiosignalSource.py
ltbio/biosignals/sources/Bitalino.py
ltbio/biosignals/sources/BrainLat.py
ltbio/biosignals/sources/E4.py
ltbio/biosignals/sources/HEM.py
ltbio/biosignals/sources/HSM.py
ltbio/biosignals/sources/MITDB.py
ltbio/biosignals/sources/Multisource.py
ltbio/biosignals/sources/Seer.py
ltbio/biosignals/sources/Sense.py
ltbio/biosignals/sources/__init__.py
ltbio/biosignals/timeseries/Event.py
ltbio/biosignals/timeseries/Frequency.py
ltbio/biosignals/timeseries/Timeline.py
ltbio/biosignals/timeseries/Timeseries.py
ltbio/biosignals/timeseries/Unit.py
ltbio/biosignals/timeseries/__init__.py
ltbio/clinical/BodyLocation.py
ltbio/clinical/Patient.py
ltbio/clinical/Semiology.py
ltbio/clinical/__init__.py
ltbio/clinical/conditions/COVID19.py
ltbio/clinical/conditions/Epilepsy.py
ltbio/clinical/conditions/MedicalCondition.py
ltbio/clinical/conditions/__init__.py
ltbio/clinical/medications/Medication.py
ltbio/clinical/medications/__init__.py
ltbio/clinical/procedures/CarpalTunnelRelease.py
ltbio/clinical/procedures/SurgicalProcedure.py
ltbio/clinical/procedures/__init__.py
ltbio/decision/BinaryDecision.py
ltbio/decision/Decision.py
ltbio/decision/DecisionMaker.py
ltbio/decision/NAryDecision.py
ltbio/decision/__init__.py
ltbio/features/FeatureExtractor.py
ltbio/features/FeatureSelector.py
ltbio/features/Features.py
LongTermBiosignals-2.0.2.dist-info/METADATA
LongTermBiosignals-2.0.2.dist-info/WHEEL
LongTermBiosignals-2.0.2.dist-info/top_level.txt
LongTermBiosignals-2.0.2.dist-info/RECORD
