Metadata-Version: 2.1
Name: LongTermBiosignals
Version: 2.0.2
Summary: Python library for easy managing and processing of large Long-Term Biosignals.
Home-page: https://github.com/jomy-kk/LTBio
Author: João Saraiva, Mariana Abreu
Author-email: joaomiguelsaraiva@tecnico.ulisboa.pt
Requires-Python: >=3.10.4
Requires-Dist: alabaster ==0.7.12
Requires-Dist: altair ==4.2.0
Requires-Dist: appdirs ==1.4.4
Requires-Dist: appnope ==0.1.3
Requires-Dist: argon2-cffi ==21.3.0
Requires-Dist: argon2-cffi-bindings ==21.2.0
Requires-Dist: astroid ==2.11.5
Requires-Dist: asttokens ==2.0.5
Requires-Dist: attrs ==21.4.0
Requires-Dist: Babel ==2.10.3
Requires-Dist: backcall ==0.2.0
Requires-Dist: backoff ==1.11.1
Requires-Dist: beautifulsoup4 ==4.11.1
Requires-Dist: bidict ==0.22.0
Requires-Dist: biosppy ==0.8.0
Requires-Dist: bleach ==5.0.1
Requires-Dist: bokeh ==2.4.3
Requires-Dist: boltons ==21.0.0
Requires-Dist: certifi ==2021.10.8
Requires-Dist: cffi ==1.15.0
Requires-Dist: cftime ==1.6.3
Requires-Dist: chardet ==4.0.0
Requires-Dist: charset-normalizer ==2.0.12
Requires-Dist: click ==8.1.3
Requires-Dist: click-spinner ==0.1.10
Requires-Dist: colorlog ==6.7.0
Requires-Dist: colorspacious ==1.1.2
Requires-Dist: commonmark ==0.9.1
Requires-Dist: cramjam ==2.5.0
Requires-Dist: cycler ==0.11.0
Requires-Dist: Cython ==0.29.32
Requires-Dist: dacite ==1.6.0
Requires-Dist: darkdetect ==0.8.0
Requires-Dist: datacommons ==1.4.3
Requires-Dist: datacommons-pandas ==0.0.3
Requires-Dist: datapane ==0.15.3
Requires-Dist: DateTime ==5.1
Requires-Dist: DateTimeRange ==1.2.0
Requires-Dist: debugpy ==1.6.0
Requires-Dist: decorator ==5.1.1
Requires-Dist: defusedxml ==0.7.1
Requires-Dist: diagrams ==0.21.1
Requires-Dist: dill ==0.3.4
Requires-Dist: docutils ==0.18.1
Requires-Dist: dominate ==2.7.0
Requires-Dist: dulwich ==0.20.46
Requires-Dist: edflib ==0.84.1
Requires-Dist: EDFlib-Python ==1.0.6
Requires-Dist: entrypoints ==0.4
Requires-Dist: executing ==0.8.3
Requires-Dist: face ==20.1.1
Requires-Dist: fastjsonschema ==2.15.3
Requires-Dist: fastparquet ==0.8.3
Requires-Dist: flake8 ==5.0.4
Requires-Dist: fonttools ==4.33.2
Requires-Dist: fpdf2 ==2.5.5
Requires-Dist: fsspec ==2022.8.2
Requires-Dist: furl ==2.1.3
Requires-Dist: furo ==2022.12.7
Requires-Dist: future ==0.18.2
Requires-Dist: gitdb ==4.0.9
Requires-Dist: GitPython ==3.1.27
Requires-Dist: glom ==22.1.0
Requires-Dist: graphviz ==0.19.2
Requires-Dist: h5py ==3.7.0
Requires-Dist: idna ==3.3
Requires-Dist: imagesize ==1.4.1
Requires-Dist: importlib-metadata ==4.12.0
Requires-Dist: importlib-resources ==5.9.0
Requires-Dist: infinity ==1.5
Requires-Dist: iniconfig ==1.1.1
Requires-Dist: ipykernel ==6.15.0
Requires-Dist: ipython ==8.4.0
Requires-Dist: ipython-genutils ==0.2.0
Requires-Dist: ipywidgets ==7.7.1
Requires-Dist: isort ==5.10.1
Requires-Dist: jedi ==0.18.1
Requires-Dist: Jinja2 ==3.1.1
Requires-Dist: joblib ==1.1.0
Requires-Dist: jsonschema ==4.6.0
Requires-Dist: jupyter ==1.0.0
Requires-Dist: jupyter-client ==7.3.4
Requires-Dist: jupyter-console ==6.4.4
Requires-Dist: jupyter-core ==4.10.0
Requires-Dist: jupyterlab-pygments ==0.2.2
Requires-Dist: jupyterlab-widgets ==1.1.1
Requires-Dist: keyring ==23.7.0
Requires-Dist: kiwisolver ==1.4.2
Requires-Dist: lazy-object-proxy ==1.7.1
Requires-Dist: lazy-loader ==0.3
Requires-Dist: littleutils ==0.2.2
Requires-Dist: lxml ==4.9.1
Requires-Dist: markdown-it-py ==2.1.0
Requires-Dist: MarkupSafe ==2.1.1
Requires-Dist: matplotlib ==3.5.1
Requires-Dist: matplotlib-inline ==0.1.3
Requires-Dist: mbstrdecoder ==1.1.0
Requires-Dist: mccabe ==0.7.0
Requires-Dist: mdit-py-plugins ==0.3.3
Requires-Dist: mdurl ==0.1.2
Requires-Dist: micawber ==0.5.4
Requires-Dist: mistune ==0.8.4
Requires-Dist: mne
Requires-Dist: mne-connectivity
Requires-Dist: mne-qt-browser ==0.6.1
Requires-Dist: monotonic ==1.6
Requires-Dist: multimethod ==1.9.1
Requires-Dist: multipledispatch ==0.6.0
Requires-Dist: munch ==2.5.0
Requires-Dist: myst-parser ==0.18.1
Requires-Dist: nbclient ==0.6.4
Requires-Dist: nbconvert ==6.5.0
Requires-Dist: nbformat ==5.4.0
Requires-Dist: neo ==0.10.2
Requires-Dist: nest-asyncio ==1.5.5
Requires-Dist: netCDF4 ==1.6.5
Requires-Dist: notebook ==6.4.12
Requires-Dist: numexpr ==2.8.3
Requires-Dist: numpy ==1.22.3
Requires-Dist: opencv-python ==4.5.5.64
Requires-Dist: orderedmultidict ==1.0.1
Requires-Dist: outdated ==0.2.2
Requires-Dist: packaging ==21.3
Requires-Dist: pandas ==1.4.2
Requires-Dist: pandas-flavor ==0.6.0
Requires-Dist: pandocfilters ==1.5.0
Requires-Dist: parso ==0.8.3
Requires-Dist: patsy ==0.5.2
Requires-Dist: pexpect ==4.8.0
Requires-Dist: pickleshare ==0.7.5
Requires-Dist: Pillow ==9.1.0
Requires-Dist: pingouin ==0.5.3
Requires-Dist: pkginfo ==1.8.3
Requires-Dist: platformdirs ==2.5.2
Requires-Dist: plotly ==5.10.0
Requires-Dist: plotly-express ==0.4.1
Requires-Dist: pluggy ==1.0.0
Requires-Dist: ply ==3.11
Requires-Dist: pooch ==1.6.0
Requires-Dist: posthog ==2.1.2
Requires-Dist: prometheus-client ==0.14.1
Requires-Dist: prompt-toolkit ==3.0.30
Requires-Dist: psutil ==5.9.1
Requires-Dist: ptyprocess ==0.7.0
Requires-Dist: pure-eval ==0.2.2
Requires-Dist: py ==1.11.0
Requires-Dist: py-cpuinfo ==8.0.0
Requires-Dist: pyarrow ==6.0.1
Requires-Dist: pycodestyle ==2.9.1
Requires-Dist: pycparser ==2.21
Requires-Dist: pydantic ==1.10.2
Requires-Dist: pyEDFlib ==0.1.30
Requires-Dist: pyflakes ==2.5.0
Requires-Dist: Pygments ==2.12.0
Requires-Dist: pylint ==2.13.9
Requires-Dist: pymatreader ==0.0.32
Requires-Dist: Pympler ==1.0.1
Requires-Dist: PyOpenGL ==3.1.7
Requires-Dist: pyparsing ==3.0.8
Requires-Dist: PyQt5
Requires-Dist: PyQt5-Qt5
Requires-Dist: PyQt5-sip
Requires-Dist: pyqtgraph
Requires-Dist: pyrsistent ==0.18.1
Requires-Dist: pytest ==7.1.2
Requires-Dist: python-dateutil ==2.8.2
Requires-Dist: pytz ==2022.1
Requires-Dist: PyYAML ==6.0
Requires-Dist: pyzmq ==23.2.0
Requires-Dist: QDarkStyle ==3.2.3
Requires-Dist: qtconsole ==5.3.1
Requires-Dist: QtPy ==2.1.0
Requires-Dist: quantities ==0.13.0
Requires-Dist: readme-renderer ==35.0
Requires-Dist: requests ==2.27.1
Requires-Dist: requests-toolbelt ==0.9.1
Requires-Dist: rfc3986 ==2.0.0
Requires-Dist: rich ==12.5.1
Requires-Dist: scikit-learn ==1.1.0
Requires-Dist: scipy ==1.8.0
Requires-Dist: scooby ==0.9.2
Requires-Dist: seaborn ==0.11.2
Requires-Dist: Send2Trash ==1.8.0
Requires-Dist: shortuuid ==1.0.9
Requires-Dist: six ==1.16.0
Requires-Dist: smmap ==5.0.0
Requires-Dist: snowballstemmer ==2.2.0
Requires-Dist: sortedcontainers ==2.4.0
Requires-Dist: soupsieve ==2.3.2.post1
Requires-Dist: Sphinx ==5.0.2
Requires-Dist: sphinx-autoapi ==2.0.1
Requires-Dist: sphinx-basic-ng ==1.0.0b1
Requires-Dist: sphinx-copybutton ==0.5.1
Requires-Dist: sphinxcontrib-applehelp ==1.0.2
Requires-Dist: sphinxcontrib-devhelp ==1.0.2
Requires-Dist: sphinxcontrib-htmlhelp ==2.0.0
Requires-Dist: sphinxcontrib-jsmath ==1.0.1
Requires-Dist: sphinxcontrib-qthelp ==1.0.3
Requires-Dist: sphinxcontrib-serializinghtml ==1.1.5
Requires-Dist: stack-data ==0.3.0
Requires-Dist: statsmodels ==0.13.2
Requires-Dist: stringcase ==1.2.0
Requires-Dist: tables ==3.7.0
Requires-Dist: tabulate ==0.8.10
Requires-Dist: tenacity ==8.1.0
Requires-Dist: terminado ==0.15.0
Requires-Dist: threadpoolctl ==3.1.0
Requires-Dist: thriftpy2 ==0.4.14
Requires-Dist: tinycss2 ==1.1.1
Requires-Dist: tomli ==2.0.1
Requires-Dist: toolz ==0.12.0
Requires-Dist: torch ==1.13.1
Requires-Dist: torchmetrics ==0.10.0
Requires-Dist: torchsummary ==1.5.1
Requires-Dist: torchvision ==0.14.1
Requires-Dist: tornado ==6.1
Requires-Dist: tqdm ==4.64.0
Requires-Dist: traces ==0.6.0
Requires-Dist: traitlets ==5.3.0
Requires-Dist: twine
Requires-Dist: typepy ==1.3.0
Requires-Dist: typing-extensions ==4.2.0
Requires-Dist: Unidecode ==1.3.6
Requires-Dist: urllib3 ==1.26.9
Requires-Dist: validators ==0.20.0
Requires-Dist: vega-datasets ==0.9.0
Requires-Dist: wcwidth ==0.2.5
Requires-Dist: webencodings ==0.5.1
Requires-Dist: wfdb ==3.4.1
Requires-Dist: wget ==3.2
Requires-Dist: widgetsnbextension ==3.6.1
Requires-Dist: wrapt ==1.14.1
Requires-Dist: xarray ==2023.12.0
Requires-Dist: xmltodict ==0.13.0
Requires-Dist: zipp ==3.8.1
Requires-Dist: zope.interface ==6.0
